setup.cfg
setup.py
ibconn/__init__.py
ibconn/ibconn.py
ibconn.egg-info/PKG-INFO
ibconn.egg-info/SOURCES.txt
ibconn.egg-info/dependency_links.txt
ibconn.egg-info/top_level.txt