Metadata-Version: 1.0
Name: ibconn
Version: 0.0.2
Summary: infoblox client library
Home-page: http://github.com/huit/python-ibconn
Author: Luke Sullivan
Author-email: luke_sullivan@harvard.edu
License: MIT
Keywords: infoblox
Platform: UNKNOWN
